pycellin/__init__.py
pycellin/custom_types.py
pycellin/utils.py
pycellin/classes/__init__.py
pycellin/classes/data.py
pycellin/classes/exceptions.py
pycellin/classes/feature.py
pycellin/classes/feature_calculator.py
pycellin/classes/lineage.py
pycellin/classes/model.py
pycellin/classes/updater.py
pycellin/graph/__init__.py
pycellin/graph/features/__init__.py
pycellin/graph/features/morphology.py
pycellin/graph/features/motion.py
pycellin/graph/features/tracking.py
pycellin/graph/features/utils.py
pycellin/io/__init__.py
pycellin/io/cell_tracking_challenge/__init__.py
pycellin/io/cell_tracking_challenge/exporter.py
pycellin/io/cell_tracking_challenge/loader.py
pycellin/io/trackmate/__init__.py
pycellin/io/trackmate/exporter.py
pycellin/io/trackmate/loader.py
pycellin/io/trackpy/__init__.py
pycellin/io/trackpy/exporter.py
pycellin/io/trackpy/loader.py
pycellin-0.4.2.dist-info/licenses/LICENSE
pycellin-0.4.2.dist-info/METADATA
pycellin-0.4.2.dist-info/WHEEL
pycellin-0.4.2.dist-info/top_level.txt
pycellin-0.4.2.dist-info/RECORD
