Metadata-Version: 2.4
Name: pycellin
Version: 0.4.2
Summary: Graph-based framework to manipulate and analyze cell lineages from cell tracking data
Author-email: Laura Xénard <laura.xenard@pasteur.fr>
Project-URL: Documentation, https://Image-Analysis-Hub.github.io/pycellin/
Project-URL: Examples, https://Image-Analysis-Hub.github.io/pycellin/notebooks/
Project-URL: Issues, https://github.com/Image-Analysis-Hub/pycellin/issues
Project-URL: Source, https://github.com/Image-Analysis-Hub/pycellin/
Classifier: Development Status :: 4 - Beta
Classifier: Programming Language :: Python :: 3
Classifier: License :: OSI Approved :: BSD License
Classifier: Operating System :: OS Independent
Classifier: Intended Audience :: Science/Research
Classifier: Intended Audience :: Developers
Classifier: Topic :: Software Development :: Libraries :: Python Modules
Classifier: Topic :: Scientific/Engineering :: Information Analysis
Requires-Python: >=3.10
License-File: LICENSE
Requires-Dist: igraph>=0.9
Requires-Dist: lxml>=5
Requires-Dist: matplotlib>=3
Requires-Dist: networkx>=3
Requires-Dist: pandas>=2
Requires-Dist: plotly>=5
Requires-Dist: scikit-image>=0.19
Requires-Dist: scipy>=1.15
Requires-Dist: shapely>=2
Provides-Extra: test
Requires-Dist: pytest>=8.3; extra == "test"
Requires-Dist: pytest-cov>=6.0; extra == "test"
Dynamic: license-file
